odoo/addons/shopinvader_api_wishlist/README.rst
odoo/addons/shopinvader_api_wishlist/__init__.py
odoo/addons/shopinvader_api_wishlist/__manifest__.py
odoo/addons/shopinvader_api_wishlist/dependencies.py
odoo/addons/shopinvader_api_wishlist/schemas.py
odoo/addons/shopinvader_api_wishlist/i18n/shopinvader_api_wishlist.pot
odoo/addons/shopinvader_api_wishlist/i18n/shopinvader_wishlist.pot
odoo/addons/shopinvader_api_wishlist/readme/CONTRIBUTORS.rst
odoo/addons/shopinvader_api_wishlist/readme/CREDITS.rst
odoo/addons/shopinvader_api_wishlist/readme/DESCRIPTION.rst
odoo/addons/shopinvader_api_wishlist/routers/__init__.py
odoo/addons/shopinvader_api_wishlist/routers/wishlists.py
odoo/addons/shopinvader_api_wishlist/security/acl_sale_product_set_wizard.xml
odoo/addons/shopinvader_api_wishlist/security/groups.xml
odoo/addons/shopinvader_api_wishlist/security/rule+acl_product_set.xml
odoo/addons/shopinvader_api_wishlist/security/rule+acl_product_set_line.xml
odoo/addons/shopinvader_api_wishlist/static/description/icon.png
odoo/addons/shopinvader_api_wishlist/static/description/index.html
odoo/addons/shopinvader_api_wishlist/tests/__init__.py
odoo/addons/shopinvader_api_wishlist/tests/common.py
odoo/addons/shopinvader_api_wishlist/tests/test_wishlist.py
odoo/addons/shopinvader_api_wishlist/wizard/__init__.py
odoo/addons/shopinvader_api_wishlist/wizard/sale_product_set_wizard.py
odoo_addon_shopinvader_api_wishlist-16.0.1.0.2.dist-info/METADATA
odoo_addon_shopinvader_api_wishlist-16.0.1.0.2.dist-info/WHEEL
odoo_addon_shopinvader_api_wishlist-16.0.1.0.2.dist-info/top_level.txt
odoo_addon_shopinvader_api_wishlist-16.0.1.0.2.dist-info/RECORD
