Metadata-Version: 2.1
Name: odoo-addon-shopinvader-api-wishlist
Version: 16.0.1.0.2
Summary: Handle shop wishlist
Home-page: https://github.com/shopinvader/odoo-shopinvader
Author: ACSONE SA/NV, Camptocamp,Odoo Community Association (OCA)
Author-email: support@odoo-community.org
License: AGPL-3
Platform: UNKNOWN
Classifier: Programming Language :: Python
Classifier: Framework :: Odoo
Classifier: Framework :: Odoo :: 16.0
Classifier: License :: OSI Approved :: GNU Affero General Public License v3
Requires-Python: >=3.10
Requires-Dist: odoo-addon-extendable-fastapi <16.1dev,>=16.0dev
Requires-Dist: odoo-addon-fastapi <16.1dev,>=16.0dev
Requires-Dist: odoo-addon-sale-wishlist <16.1dev,>=16.0dev
Requires-Dist: odoo-addon-shopinvader-api-security-sale <16.1dev,>=16.0dev
Requires-Dist: odoo-addon-shopinvader-filtered-model <16.1dev,>=16.0dev
Requires-Dist: odoo-addon-shopinvader-sale-cart <16.1dev,>=16.0dev
Requires-Dist: odoo-addon-shopinvader-schema-sale <16.1dev,>=16.0dev
Requires-Dist: odoo <16.1dev,>=16.0a
